test/__init__.py
test/test_classification.py
test/test_regression.py
th_sklearn_json/__init__.py
th_sklearn_json/classification.py
th_sklearn_json/csr.py
th_sklearn_json/regression.py
th_sklearn_json-0.1.0.dist-info/LICENSE
th_sklearn_json-0.1.0.dist-info/METADATA
th_sklearn_json-0.1.0.dist-info/WHEEL
th_sklearn_json-0.1.0.dist-info/top_level.txt
th_sklearn_json-0.1.0.dist-info/RECORD
