Metadata-Version: 2.1
Name: th-sklearn-json
Version: 0.1.0
Summary: A safe, transparent way to share and deploy scikit-learn models. Original by Mathieu Rodrigue
Home-page: https://github.com/mignev/sklearn-json
Author: Marian Ignev
Author-email: dev@teachablehub.com
License: UNKNOWN
Platform: UNKNOWN
Classifier: Programming Language :: Python :: 3
Classifier: License :: OSI Approved :: MIT License
Classifier: Operating System :: OS Independent
Requires-Python: >=3.5
Requires-Dist: scikit-learn (>=0.21.3)
